
{
    "id": "SlimySewers",
    "require-matching-doors": false,
    "object-groups": [
        "SlimySewers/objectgroup"
    ],
    
        "resource-packs": [
        "SlimySewers"
    ],
    
    "visual-theme": "cave",
    "sound-theme": "cave",
    "prop-density": 1,
    "mob-groups": [
         {
            "#": "============== PUMPKIN MIX ==============",
            "id": "pumpkin-mix",
            "types": [
                {"type": "zombie", "weight": 1},
                {"type": "skeleton", "weight": 1},
                {"type": "vindicator", "weight": 1},
                {"type": "creeper", "weight": 0.3, "max": 4},
                {"type": "spider", "weight": 0.5, "max": 7},
                {"type": "evoker", "weight": 0.2, "max": 2},
                {"type": "enchanter", "weight": 0.2, "max": 2},
                {"type": "chickenjockey", "weight": 0.1, "max": 3}
            ],
             "pick-types": [3, 4]
        },
        {
            "#": "============== PUMPKIN MIX ==============",
            "id": "pumpkin-casters",
            "types": [
                {"type": "skeleton", "weight": 1},
                {"type": "vindicator", "weight": 1},
                {"type": "evoker", "weight": 0.5, "max": 2},
                {"type": "enchanter", "weight": 0.5, "max": 2}
            ],
             "pick-types": [2, 3]
        },
        {
            "#": "============== RANDOM ARENA ==============",
            "id": "random-arena",
            "types": [
                {"type": "skeleton", "weight": 1},
                {"type": "vindicator", "weight": 1},
                {"type": "evoker", "weight": 0.5, "max": 2},
                {"type": "enchanter", "weight": 0.5, "max": 2}
            ],
             "pick-types": [2, 3]
        },
        {
            "#": "============== ILLAGER EVOKER ==============",
            "id": "illagerevoker-group",
            "types": [
                {"type": "evoker", "weight": 1, "min": 1, "max": 1},
                {"type": "vindicator", "weight": 3, "min": 1}        
            ]
        },
        {
            "#": "============== ILLAGER ENCHANTER ==============",
            "id": "illagerenchanter-group",
            "types": [
                {"type": "enchanter", "weight": 1, "min": 1, "max": 1},
                {"type": "vindicator", "weight": 3, "min": 1}
            ]
        },
        {
            "#": "============== ILLAGER DUO ENCHANTER ==============",
            "id": "illagerenchanter-duo-group",
            "types": [
                {"type": "enchanter", "weight": 1, "min": 2, "max": 2},
                {"type": "vindicator", "weight": 3, "min": 2}
            ]
        },
        {
            "#": "============== MINIARENA SINGLES ==============",
            "id": "miniarena-singles",
            "types": [
                {"type": "pillager", "weight": 1, "min": 1},
                {"type": "vindicator", "weight": 1, "min": 1},
                {"type": "skeleton", "weight": 1, "min": 1}
            ],
            "pick-types": [1,3]
        },
        {
            "#": "============== VINDICATOR GROUP ==============",
            "id": "vindicator-group",
            "types": [
                {"type": "vindicator", "min": 1}
            ]
        },
        {
            "#": "============== SPIDER GROUP ==============",
            "id": "spiders",
            "types": [
                {"type": "spider", "min": 1}
            ]
        }
    ],
    "#dm" : "density:Float {only, add}: WeightedStringArray, not: StringArray",
    "default-mobs": {
        "only": [
            "pumpkin-mix",
            {"id": "pumpkin-casters", "weight": 0.5}
        ]
    },
    "#tg": "SlimySewers",
    "tiles": [
        {
            "id": "sls_start",
            "rotations": 0
        },
        {
            "id": "grandroom001",
            "rotations": [0,270],
            "challenges": [ "miniarena_noloot" ]
        },
        {
            "id": "stairs001",
            "rotations": [0,270],
            "entry-door": "enter"
        },
        {
            "id": "sls_inventory001",
            "rotations": [0,90]
        },
        {
            "id": "outdoor_entrance001",
            "rotations": 0
        },
        {
            "id": "outdoor_start",
            "rotations": 0
        },
        {
            "id": "cinematic1",
            "rotations": 0
        },
        {
            "id": "cinematic2",
            "entry-door": "enter"
        },
        {
            "id": "cinematic_start",
            "rotations": 0
        },
        {
            "id": "outdoor_caveentrance001",
            "rotations": 0,
            "entry-door": "enter"
        },
        {
            "id": "sls_arena001",
            "entry-door": "enter"
        },
        {
            "id": "sls_clicky001",
            "entry-door": "enter"
        },
        {
            "id": "sls_sidepath_clicky001",
            "challenges": [ "sidepath_clicky001" ]
        },
        {
            "id": "sls_sidepath_arena001",
            "challenges": [ "sidepath_arena001" ]
        },
        {
            "id": "miniarena001",
            "challenges": [ "miniarena_noloot" ]
        }
    ],
    "tile-groups": [
        {
            "#": "Start",
            "id": "start",
            "tiles": ["sls_start"]
        },
        {
            "#": "OutdoorStart",
            "id": "outdoor_start",
            "tiles": ["outdoor_start"]
        },
        {
            "#": "CaveEntrance",
            "id": "outdoor_cave",
            "tiles": ["outdoor_caveentrance001"]
        },
        {
            "#": "StartHallway",
            "id": "start_hallway",
            "tiles": ["tile_start001"]
        },
        {
            "#": "OutdoorEntrance",
            "id": "outdoor_entrance",
            "tiles": ["outdoor_entrance001"]
        },
        {
            "#": "GrandRoom",
            "id": "grandroom",
            "tiles": ["grandroom001"]
        },
         {
            "#": "Stairs",
            "id": "stairs",
            "tiles": ["stairs001"]
        },
        {
            "#": "hallway",
            "id": "hallway",
            "tiles": ["tile001","tile002","tile003"]
        },
        {
            "#": "hallwaysidepath",
            "id": "hallwaysidepath",
            "tiles": ["miniarena001"]
        },
        {
            "#": "hallwaycrossroad",
            "id": "hallwaycrossroad",
            "tiles": ["tile003"]
        },
        {
            "#": "End",
            "id": "end",
            "tiles": ["sls_end"]
        },
        {
            "#": "Inventory",
            "id": "inventory",
            "tiles": ["sls_inventory001","tile001","tile002"]
        },
        {
            "#": "Tiles",
            "id": "tiles",
            "tiles": ["sls_tile001","sls_tile002","sls_tile003","sls_tile004","sls_tile005","sls_tile006","sls_tile007","sls_tile008","sls_tile009"]
        },
        {
            "#": "Objectives",
            "id": "objectives",
            "tiles": ["sls_arena001", "sls_clicky001"]
        },
        {
            "#": "Plaza",
            "id": "plaza1",
            "tiles": ["sls_plaza001", "sls_plaza002", "sls_plaza003"]
        },
        {
            "#": "Plaza2",
            "id": "plaza2",
            "tiles": ["sls_plaza_large001"]
        },
        {
            "#": "Sidepath",
            "id": "sidepath",
            "tiles": ["sls_tile001","sls_tile002","sls_tile003"]
        },
        {
            "#": "Minisidepath",
            "id": "minisidepath",
            "tiles": ["sls_minisidepath001", "sls_minisidepath002"]
        },
        {
            "#": "Sidepath2",
            "id": "sidepath2",
            "tiles": ["sls_tile001","sls_tile002","sls_tile003","sls_tile004","sls_tile005","sls_tile006","sls_tile007","sls_tile008","sls_tile009","sls_sidepath_arena001","sls_sidepath_clicky001"]
        },
        {
            "#": "SidepathChallenge",
            "id": "sidepathchallenge",
            "tiles": ["sls_tile005","sls_tile008","sls_tile009","sls_sidepath_arena001","sls_sidepath_clicky001"]
        },
        {
            "#": "PlazaChallenge",
            "id": "plazachallenge",
            "tiles": ["sls_plaza001", "sls_plaza002","sls_plaza003","sls_sidepath_arena001","sls_sidepath_clicky001"]
        }
    ],
    "stretches": [
        {
        "tiles": ["cinematic1"]
        },
        {
        "tiles": ["cinematic2"]
        },
        {
        "tiles": ["cinematic3"]
        }
        /*{
            "id": "start",
            "tile-groups": ["outdoor_start"],
            "sound-theme": "silent",
            "visual-theme": "cave_dark"
        },
        {
            "id": "outdoor_cave",
            "tile-groups": ["outdoor_cave"],
            "sound-theme": "silent",
            "visual-theme": "cave_dark"
        },
        {
            "id": "hallway",
            "tile-groups": ["hallway"],
            "sound-theme": "silent",
            "length": 1,
            "visual-theme": "cave_dark"
        },
        {
            "id": "hallwaycrossroad",
            "tile-groups": ["hallwaycrossroad"],
            "sound-theme": "silent",
            "visual-theme": "cave_dark",
            "side-paths": {
                "probability": 1,
                "default": {
                    "max-length": [1,2],
                    "dead-ends": ["corridor_deadend001","corridor_deadend002","corridor_deadend003"],
                    "tile-groups": ["hallwaysidepath"]
                }
            }
        }, 
        {
            "id": "grandroom",
            "tile-groups": ["grandroom"],
            "sound-theme": "silent",
            "visual-theme": "cave_dark"
        },
        {
            "id": "hallway",
            "tile-groups": ["hallway"],
            "length": 2,
            "sound-theme": "silent",
            "visual-theme": "cave_dark"
        },
        {
            "id": "stairs",
            "tile-groups": ["stairs"],
            "sound-theme": "silent",
            "visual-theme": "cave_dark", 
            "mobs": {
                "density": 1,
                "only": ["spiders"]
            }
        },
        {
            "id": "tiles_1",
            "tile-groups": ["tiles"],
            "length": 3,
            "sound-theme": "silent",
            "visual-theme": "cave_dark",
            "mobs": {
                "density": 0.35,
                "only": ["pumpkin-mix","pumpkin-casters"]
            }
        },
        {
            "id": "inventory_1",
            "tile-groups": ["inventory"],
            "length": 1,
            "sound-theme": "silent",
            "visual-theme": "cave_dark"
        },
        {
            "id": "objectives",
            "tile-groups": ["objectives"],
            "length": 1,
            "sound-theme": "silent",
            "visual-theme": "cave_dark",
            "mobs": {
                "density": 1,
                "only": [ "illagerenchanter-duo-group","random-arena", "vindicator-group"]
            },
             "side-paths": {
                "probability": 1,
                "default": {
                    "max-length": [1,2],
                    "dead-ends": ["sls_minisidepath_deadend001"],
                    "tile-groups": ["Minisidepath"]
                }
            }
        },
        {
            "id": "tiles_2",
            "tile-groups": ["tiles"],
            "length": 2,
            "sound-theme": "silent",
            "visual-theme": "cave_dark",
            "mobs": {
                "density": 0.45,
                "only": ["pumpkin-mix","pumpkin-casters"]
            },
             "side-paths": {
                "probability": 0.5,
                "default": {
                    "max-length": [1,2],
                    "dead-ends": ["deadend001"],
                    "tile-groups": ["sidepath"]
                }
            }
        },
        {
            "id": "plaza_1",
            "tile-groups": ["plazachallenge"],
            "prop-groups": ["plaza_prop"],
            "length": 1,
            "sound-theme": "silent",
            "visual-theme": "cave_dark",
            "mobs": {
                "density": 0.6,
                "only": ["pumpkin-mix","pumpkin-casters","random-arena"]
            }
        },
        {
            "id": "tiles_3",
            "tile-groups": ["tiles"],
            "length": 1,
            "sound-theme": "silent",
            "visual-theme": "cave_dark",
            "mobs": {
                "density": 0.25
            },
            "side-paths": {
                "probability": 0.5,
                "default": {
                    "max-length": [1,2],
                    "dead-ends": ["deadend001"],
                    "tile-groups": ["sidepath"]
                }
            }
        },
        {
            "id": "plaza_2",
            "tile-groups": ["plaza2"],
            "prop-groups": ["plaza_prop"],
            "length": 1,
            "sound-theme": "silent",
            "visual-theme": "cave_dark",
            "mobs": {
                "density": 1,
                "only": ["pumpkin-mix","pumpkin-casters"]
            },
            "side-paths": {
                "probability": 1,
                "default": {
                    "max-length": [1,3],
                    "dead-ends": ["deadend001"],
                    "tile-groups": ["sidepathchallenge"]
                }
            }
        },
        {
            "id": "end",
            "tile-groups": ["end"],
            "sound-theme": "silent",
            "visual-theme": "cave_dark"
        }*/
    ],
    "objectives": [
        /*{
            "name": "name_fight_stuff",
            "description": "description_find_the_secret_exit",
            "displayMode": "MainObjective",
            "optional": true,
            "gauntlet": {
                "end-region": "objectives.*.arenaentrance_1"
            }
        },
        {
            "name": "name_free_the_prisoners",
            "description": "description_find_the_prisoners",
            "displayMode": "MainObjective",
            "optional": true,
            "gauntlet": {
                "end-region": "objectives.*.arenaentrance_2"
            }
        },
        {
            "name": "name_fight_stuff",
            "description": "description_survive_the_ambush!",
            "displayMode": "MainObjective",
            "optional": true,
            "arena": {
                "stretch": "objectives",
                "interval": 20,
                "rest-interval": 4,
                "waves": [
                    [1, "pumpkin-casters"]
                ]
            }
        },
        {
            "name": "name_the_clicky_puzzle",
            "description": "description_click_all_the_things!",
            "displayMode": "MainObjective",
            "optional": true,
            "click": {
                "object": "Decor/Prefabs/CapturedVillager/BP_CapturedVillager",
                "count": 3,
                "locations": [
                    "objectives.*.clicky1",
                    "objectives.*.clicky2",
                    "objectives.*.clicky3"
                ],
                "locked-doors": [
                    "objectives.*.clickygate"
                ]
            }
        },      
        {
            "name": "name_level_placeholder",
            "description": "description_find_the_secret_exit",
            "displayMode": "MainObjective",
            "gauntlet": {
                "end-region": "end.*.goal"
            }
        },*/
        {
            "name": "name_level_placeholder",
            "description": "description_find_the_secret_exit",
            "displayMode": "MainObjective",
            "gauntlet": {
                "end-region": "*.*.goal"
            }
        }
    ],
    "challenges": [
        {
            "id": "sidepath_clicky001",
            "trigger": "*.*.challenge",
            "reward": {
                "region": "*.*.challengeloot",
                "object": "Decor/Prefabs/RewardChest/BP_FancyChest_Reward"
            },
            "click": {
                "object": "Decor/Prefabs/CapturedVillager/BP_CapturedVillager",
                "count": 2,
                "locations": [
                    "*.*.clicky1",
                    "*.*.clicky2"
                ]
            }
        },
        {
            "id": "sidepath_arena001",
            "trigger": "*.*.challenge",
            "reward": {
                "object": "Decor/Prefabs/RewardChest/BP_EmeraldChest_Reward"
            },
            "arena": {
                "prespawn-mob": "",                
                "stretch": "*",
                "interval": 20,
                "rest-interval": 4,
                "start-time": 2.0,
                "waves": [
                    [1, "pumpkin-casters"]
                ]
            }
        },
        {
            "id": "miniarena_noloot",
            "trigger": "*.*.challenge",
            "reward": {
                "region": "*.*.challengeloot",
                "object": "Decor/Prefabs/RewardChest/BP_EmeraldChest_Reward"
            },
            "arena": {
                "stretch": "*",
                "interval": 2,
                "rest-interval": 0,
                "start-time": 2.0,
                "prespawn-mob": "",
                "waves": [
                    [1, "miniarena-singles"],
                    [1, "miniarena-singles"]/*,
                    [1, "miniarena-singles"],
                    [1, "miniarena-singles"],
                    [1, "miniarena-singles"],
                    [1, "miniarena-singles"],
                    [1, "miniarena-singles"],
                    [1, "miniarena-singles"],
                    [1, "miniarena-singles"],
                    [1, "miniarena-singles"],
                    [1, "miniarena-singles"],
                    [1, "miniarena-singles"],
                    [1, "miniarena-singles"],
                    [1, "miniarena-singles"],
                    [1, "miniarena-singles"],
                    [1, "miniarena-singles"],
                    [1, "miniarena-singles"],
                    [1, "miniarena-singles"],
                    [1, "miniarena-singles"],
                    [1, "miniarena-singles"],
                    [1, "miniarena-singles"]*/
                ],
                "gate": {
                    "object": "Decor/Prefabs/ArenaEye/BP_ArenaEye",
                    "start-unlocked": true
                }
            }
        }
    ]
}
